spective_systembars/__init__.py
spective_systembars/systembars.py
spective_systembars-0.92.dist-info/METADATA
spective_systembars-0.92.dist-info/WHEEL
spective_systembars-0.92.dist-info/license_files/LICENSE
spective_systembars-0.92.dist-info/RECORD
