Metadata-Version: 2.1
Name: spective-systembars
Version: 0.92
Summary: PySide2 Qt widgets for displaying system stats such as CPU,GPU and RAM load as bars (e.g. inside the status bar)
Project-URL: Homepage, https://www.spective.de
Author-email: speCTive GmbH <info@spective.de>
License: Copyright (c) 2022 speCTive GmbH, Guntramstr. 15, Freiburg, Germany
Classifier: License :: OSI Approved :: MIT License
Classifier: Operating System :: OS Independent
Classifier: Programming Language :: Python :: 3
Requires-Python: >=3.7
